pytest_allure_intersection/__init__.py
pytest_allure_intersection-1.0.0.dist-info/entry_points.txt
pytest_allure_intersection-1.0.0.dist-info/LICENSE
pytest_allure_intersection-1.0.0.dist-info/WHEEL
pytest_allure_intersection-1.0.0.dist-info/METADATA
pytest_allure_intersection-1.0.0.dist-info/RECORD
